AUTHORS
CHANGELOG
LICENSE
MANIFEST.in
README.rst
setup.py
activitysync/__init__.py
activitysync/admin.py
activitysync/managers.py
activitysync/models.py
activitysync/tests.py
activitysync/management/__init__.py
activitysync/management/commands/__init__.py
activitysync/management/commands/updateactivities.py
activitysync/media/README
activitysync/media/networks/delicious.png
activitysync/media/networks/digg.png
activitysync/media/networks/email.png
activitysync/media/networks/facebook.png
activitysync/media/networks/flickr.png
activitysync/media/networks/google.png
activitysync/media/networks/googlereader.png
activitysync/media/networks/hulu.png
activitysync/media/networks/linkedin.png
activitysync/media/networks/picasa.png
activitysync/media/networks/posterous.png
activitysync/media/networks/reddit.png
activitysync/media/networks/rss.png
activitysync/media/networks/tumblr.png
activitysync/media/networks/twitter.png
activitysync/media/networks/windowslive.png
activitysync/media/networks/youtube.png
activitysync/migrations/0001_initial.py
activitysync/migrations/0002_auto__add_provider__add_field_activity_provider.py
activitysync/migrations/0003_convert_to_provider_objects.py
activitysync/migrations/0004_auto__del_field_activity_source.py
activitysync/migrations/__init__.py
activitysync/providers/__init__.py
activitysync/providers/googlereader.py
activitysync/providers/redditprovider.py
activitysync/providers/twitterprovider.py
activitysync/templates/activitysync/activities_tag.html
activitysync/templatetags/__init__.py
activitysync/templatetags/activitysync_extras.py
django_activitysync.egg-info/PKG-INFO
django_activitysync.egg-info/SOURCES.txt
django_activitysync.egg-info/dependency_links.txt
django_activitysync.egg-info/top_level.txt