Metadata-Version: 1.0
Name: django-activitysync
Version: 0.2.2
Summary: Fast, easy, and extensible social activity aggregation for Django projects
Home-page: https://bitbucket.org/dancarroll/django-activitysync
Author: Dan Carroll
Author-email: dan@dancarroll.org
License: BSD
Download-URL: https://bitbucket.org/dancarroll/django-activitysync/downloads
Keywords: django,social,activity,application,twitter,reddit,google reader
Platform: UNKNOWN
Classifier: Framework :: Django
Classifier: Development Status :: 4 - Beta
Classifier: Topic :: Internet
Classifier: Intended Audience :: Developers
Classifier: Environment :: Web Environment
Classifier: Programming Language :: Python
Classifier: Programming Language :: Python :: 2.6
Classifier: Programming Language :: Python :: 2.7
Classifier: License :: OSI Approved :: BSD License
Classifier: Operating System :: OS Independent
